[
    {
        "id": 0,
        "image": "images/tiles/38.jpg",
        "grid": [
            [0,0,0,0],
            [0,0,0,0],
            [0,2,0,0],
            [0,0,0,0]
        ],
        "arrow": true,
        "skull": true,
        "name":  null

    },

    {
        "id": 1,
        "image":"images/tiles/39.jpg",           
        "grid": [
            [1,1,1,1],
            [0,0,0,0],
            [0,0,2,0],
            [1,0,0,1]
        ],
        "arrow":true,
        "skull":false,
        "name":  null
    },

    {
        "id": 2,
        "image":"images/tiles/11.jpg",           
        "grid": [
            [1,1,1,1],
            [0,0,2,1],
            [0,0,0,1],
            [0,0,0,1]
        ],
        "arrow":false,
        "skull":true,
        "name":  "Crypt Corner 6-10"
    },

   

    {
        "id": 3,
        "image":"images/tiles/37.jpg",           
        "grid": [
            [1,0,2,0],
            [1,0,0,0],
            [1,0,0,0],
            [1,0,0,0]
        ],
        "arrow":false,
        "skull":false,
        "name":  "Workshop"
    },

    {
        "id": 4,
        "image":"images/tiles/42.jpg",           
        "grid": [
            [0,0,0,1],
            [0,2,0,1],
            [0,0,0,1],
            [0,0,0,1]
        ],
        "arrow":true,
        "skull":true,
        "name":  "Arcrane Circle"
    },

    {
        "id": 5,
        "image":"images/tiles/40.jpg",           
        "grid": [
            [1,0,0,1],
            [1,2,0,0],
            [1,0,0,0],
            [1,0,0,1]
        ],
        "arrow":false,
        "skull":true,
        "name":  null
    },

    {
        "id": 6,
        "image":"images/tiles/5.jpg",           
        "grid": [
            [0,0,0,1],
            [0,2,0,0],
            [0,0,0,0],
            [0,0,0,1]
        ],
        "arrow":true,
        "skull":true,
        "name":  null
    },

    {
        "id": 7,
        "image":"images/tiles/3.jpg",           
        "grid": [
            [1,1,1,1],
            [0,0,0,0],
            [0,2,0,0],
            [0,0,0,0]
        ],
        "arrow":true,
        "skull":true,
        "name": "Crypt of Sergei Von Zarovich"
    },

    {
        "id": 8 ,
        "image":"images/tiles/28.jpg",           
        "grid": [
            [1,1,1,1],
            [0,0,0,1],
            [0,2,0,1],
            [0,0,0,1]
        ],
        "arrow":true,
        "skull":false,
        "name": "Crypt of Artimus"
    },

    {
        "id": 9,
        "image":"images/tiles/6.jpg",           
        "grid": [
            [0,0,0,0],
            [0,2,0,0],
            [0,0,0,0],
            [0,0,0,0]
        ],
        "arrow":true,
        "skull":true,
        "name": null
    },

    {
        "id": 10,
        "image":"images/tiles/21.jpg",           
        "grid": [
            [1,0,0,1],
            [0,0,2,1],
            [0,0,0,1],
            [1,0,0,1]
        ],
        "arrow":false,
        "skull":true,
        "name": null
    },

    {
        "id": 11,
        "image":"images/tiles/2.jpg",           
        "grid": [
            [1,1,1,1],
            [1,0,0,0],
            [1,0,2,0],
            [1,0,0,0]
        ],
        "arrow":true,
        "skull":false,
        "name": "Prince Auriels Crypt"
    },

    {
        "id": 12,
        "image":"images/tiles/41.jpg",           
        "grid": [
            [1,1,1,1],
            [1,0,0,0],
            [1,2,0,0],
            [1,0,0,0]
        ],
        "arrow":true,
        "skull":true,
        "name": "Crypt Corner 11-15"
        },

        {
            "id": 13,
            "image":"images/tiles/9.jpg",           
            "grid": [
                [0,2,0,1],
                [0,0,0,1],
                [0,0,0,1],
                [0,0,0,1]
            ],
            "arrow":false,
            "skull":false,
            "name": "Dark Fountain"
        },

        {
            "id": 14,
            "image":"images/tiles/36.jpg",           
            "grid": [
                [1,0,0,1],
                [0,2,0,1],
                [0,0,0,1],
                [1,0,0,1]
            ],
            "arrow":false,
            "skull":true,
            "name": null
        },

        {
            "id": 15,
            "image":"images/tiles/12.jpg",           
            "grid": [
                [1,0,0,1],
                [0,0,0,0],
                [0,2,0,0],
                [1,0,0,1]
            ],
            "arrow":true,
            "skull":true,
            "name": null
        },

        {
            "id": 16,
            "image":"images/tiles/1.jpg",           
            "grid": [
                [1,1,1,1],
                [0,0,0,1],
                [0,0,2,1],
                [1,0,0,1]
            ],
            "arrow":true,
            "skull":true,
            "name": "Crypt Corner 16-20"
        },

        {
            "id": 17,
            "image":"images/tiles/8.jpg",           
            "grid": [
                [1,0,0,1],
                [0,0,2,0],
                [0,0,0,0],
                [0,0,0,0]
            ],
            "arrow":true,
            "skull":true,
            "name": "Kings Crypt"
        },

        {
            "id": 18,
            "image":"images/tiles/17.jpg",           
            "grid": [
                [1,1,1,1],
                [0,0,0,0],
                [0,0,2,0],
                [0,0,0,0]
            ],
            "arrow":true,
            "skull":true,
            "name": "Crypt of Barov and Ravenovia"
        },

        {
            "id": 19,
            "image":"images/tiles/15.jpg",           
            "grid": [
                [1,1,1,1],
                [1,0,0,0],
                [1,0,0,2],
                [1,0,0,0]
            ],
            "arrow":false,
            "skull":false,
            "name": "Rotting Nook"
        },

        {
            "id": 20,
            "image":"images/tiles/7.jpg",           
            "grid": [
                [1,0,0,1],
                [0,0,0,1],
                [0,2,0,1],
                [0,0,0,1]
            ],
            "arrow":true,
            "skull":true,
            "name": null
        },

        {
            "id": 21,
            "image":"images/tiles/18.jpg",           
            "grid": [
                [1,0,0,1],
                [1,0,0,0],
                [1,0,0,2],
                [1,0,0,0]
            ],
            "arrow":true,
            "skull":true,
            "name": "Ireena Kolyana's Crypt"
        },

        {
            "id": 22,
            "image":"images/tiles/16.jpg",           
            "grid": [
                [1,0,0,0],
                [0,0,2,0],
                [0,0,0,0],
                [1,0,0,0]
            ],
            "arrow":true,
            "skull":true,
            "name": null
        },

        {
            "id": 23,
            "image":"images/tiles/14.jpg",           
            "grid": [
                [0,0,0,1],
                [0,0,0,1],
                [2,0,0,1],
                [0,0,0,1]
            ],
            "arrow":true,
            "skull":true,
            "name": "Lonely Crypt "
        },

        {
            "id": 24,
            "image":"images/tiles/23.jpg",           
            "grid": [
                [1,0,0,0],
                [1,0,0,0],
                [1,2,0,0],
                [1,0,0,0]
            ],
            "arrow":false,
            "skull":true,
            "name": "Chapel"
        },

        {
            "id": 25,
            "image":"images/tiles/4.jpg",           
            "grid": [
                [1,0,0,1],
                [1,0,2,0],
                [1,0,0,0],
                [1,0,0,1]
            ],
            "arrow":false,
            "skull":true,
            "name": null
        },

        {
            "id": 26,
            "image":"images/tiles/13.jpg",           
            "grid": [
                [1,0,0,1],
                [1,0,0,1],
                [1,0,2,1],
                [1,0,0,1]
            ],
            "arrow":false,
            "skull":false,
            "name": null
        },

        {
            "id": 27,
            "image":"images/tiles/24.jpg",           
            "grid": [
                [1,0,0,1],
                [1,0,2,1],
                [1,0,0,1],
                [1,0,0,1]
            ],
            "arrow":false,
            "skull":false,
            "name": null
        },

        {
            "id": 28,
            "image":"images/tiles/22.jpg",           
            "grid": [
                [1,0,0,1],
                [1,0,2,1],
                [1,0,0,1],
                [1,0,0,1]
            ],
            "arrow":true,
            "skull":false,
            "name": null
        },

        {
            "id": 29,
            "image":"images/tiles/20.jpg",           
            "grid": [
                [1,1,1,1],
                [0,0,0,0],
                [0,2,0,0],
                [0,0,0,0]
            ],
            "arrow":false,
            "skull":true,
            "name": "Strahds Crypt"
        },

        {
            "id": 30,
            "image":"images/tiles/29.jpg",           
            "grid": [
                [1,1,1,1],
                [0,0,0,1],
                [2,0,0,1],
                [0,0,0,1]
            ],
            "arrow":false,
            "skull":false,
            "name": "Secret Stairway"
        },

        {
            "id": 31,
            "image":"images/tiles/27.jpg",           
            "grid": [
                [1,1,1,1],
                [1,2,0,0],
                [1,0,0,0],
                [1,0,0,0]
            ],
            "arrow":false,
            "skull":true,
            "name": "Crypt Corner 1-5 "
        },

        {
            "id": 32,
            "image":"images/tiles/19.jpg",           
            "grid": [
                [1,0,0,1],
                [1,0,0,1],
                [1,0,2,1],
                [1,0,0,1]
            ],
            "arrow":true,
            "skull":false,
            "name": null
        },

        {
            "id": 33,
            "image":"images/tiles/10.jpg",           
            "grid": [
                [1,0,0,1],
                [1,0,2,1],
                [1,0,0,1],
                [1,0,0,1]
            ],
            "arrow":false,
            "skull":true,
            "name": null
        },

        {
            "id": 34,
            "image":"images/tiles/30.jpg",           
            "grid": [
                [1,0,0,1],
                [1,0,0,1],
                [1,2,0,1],
                [1,0,0,1]
            ],
            "arrow":true,
            "skull":false,
            "name": null
        },

        {
            "id": 35,
            "image":"images/tiles/26.jpg",           
            "grid": [
                [1,1,1,1],
                [0,0,0,2],
                [0,0,0,0],
                [0,0,0,0]
            ],
            "arrow":false,
            "skull":true,
            "name": "Laboratory"
        },

        {
            "id": 36,
            "image":"images/tiles/25.jpg",           
            "grid": [
                [1,0,0,1],
                [1,2,0,1],
                [1,0,0,1],
                [1,0,0,1]
            ],
            "arrow":true,
            "skull":false,
            "name": null
        },

        {
            "id": 37,
            "image":"images/tiles/33.jpg",           
            "grid": [
                [0,0,0,0],
                [0,0,2,0],
                [0,0,0,0],
                [0,0,0,0]
            ],
            "arrow":true,
            "skull":true,
            "name": null
        },

        {
            "id": 38,
            "image":"images/tiles/31.jpg",           
            "grid": [
                [1,1,1,1],
                [0,2,0,0],
                [0,0,0,0],
                [0,0,0,0]
            ],
            "arrow":false,
            "skull":true,
            "name": "Fetid Den"
        },
        {
            "id": 39,
            "image":"images/tiles/32.jpg",           
            "grid": [
                [1,0,0,0],
                [1,0,0,0],
                [1,0,2,0],
                [1,0,0,0]
            ],
            "arrow":false,
            "skull":true,
            "name": null
        },
        {
            "id": 40,
            "image":"images/tiles/35start.jpg",           
            "grid": [
                [0,0,0,0],
                [2,0,0,0],
                [0,0,0,0],
                [0,0,0,0]
            ],
            "arrow":false,
            "skull":false,
            "name": "Start 2"
        },
        {
            "id": 41,
            "image":"images/tiles/34start.jpg",           
            "grid": [
                [0,0,0,0],
                [0,0,0,2],
                [0,0,0,0],
                [1,1,1,1]
            ],
            "arrow":false,
            "skull":false,
            "name": "Start"
        }
]